MANIFEST.in
README.rst
setup.cfg
setup.py
gaenv/__init__.py
gaenv/__main__.py
gaenv.egg-info/PKG-INFO
gaenv.egg-info/SOURCES.txt
gaenv.egg-info/dependency_links.txt
gaenv.egg-info/entry_points.txt
gaenv.egg-info/not-zip-safe
gaenv.egg-info/requires.txt
gaenv.egg-info/top_level.txt