Metadata-Version: 1.1
Name: gaenv
Version: 0.1.6
Summary: Tool to manage packages for google app engine
Home-page: http://github.com/faisalraja/gaenv
Author: Faisal Raja
Author-email: support@altlimit.com
License: MIT
Keywords: google app engine environment tool
Platform: UNKNOWN
Classifier: Development Status :: 3 - Alpha
Classifier: Environment :: Console
Classifier: Intended Audience :: Developers
Classifier: Programming Language :: Python
Classifier: License :: OSI Approved :: MIT License
